Metadata-Version: 2.4
Name: adafruit-circuitpython-adxl37x
Version: 1.2.5
Summary: A CircuitPython driver for the ADXL37x family of accelerometers
Author-email: Adafruit Industries <circuitpython@adafruit.com>
License: MIT
Project-URL: Homepage, https://github.com/adafruit/Adafruit_CircuitPython_ADXL37x.git
Keywords: adafruit,blinka,circuitpython,micropython,adxl37x,adxl375,motion,acceleration,i2c,spi,triple,axis
Classifier: Intended Audience :: Developers
Classifier: Topic :: Software Development :: Libraries
Classifier: Topic :: Software Development :: Embedded Systems
Classifier: Topic :: System :: Hardware
Classifier: License :: OSI Approved :: MIT License
Classifier: Programming Language :: Python :: 3
License-File: LICENSE
Requires-Dist: Adafruit-Blinka
Requires-Dist: adafruit-circuitpython-adxl34x
Requires-Dist: adafruit-circuitpython-busdevice
Provides-Extra: optional
Dynamic: license-file
